src/commands/__init__.py
src/commands/build.py
src/commands/deploy.py
src/commands/list.py
src/commands/pull.py
src/consts.py
src/lib/__init__.py
src/lib/adb.py
src/lib/apk/__init__.py
src/lib/apk/build.py
src/lib/apk/manifest.py
src/lib/apk/versions.py
src/lib/aws.py
src/lib/subprocess.py
src/lib/webhook.py
src/main.py
cr_apk-0.0.1rc2.dist-info/METADATA
cr_apk-0.0.1rc2.dist-info/WHEEL
cr_apk-0.0.1rc2.dist-info/entry_points.txt
cr_apk-0.0.1rc2.dist-info/RECORD
